Workbook

Sheet Dashboard Final
B2: DASHBOARD EJECUTIVO DE VENTAS | J2: Sistema de BI en Excel · Retail Fuente: Datos_Crudos · 360 operaciones
B4: =Aux_Dashboard!$B$31 -> Año 2024 · Mes: (Todos) · Región: (Todos) · Categoría: (Todos) · Estado: (Todos)
B6: VENTAS NETAS | E6: % MARGEN | H6: UNIDADES VENDIDAS | K6: TICKET PROM. POR UNIDAD
B7: =Aux_Dashboard!$B$24 -> 9.8759678e+08 | E7: =Aux_Dashboard!$E$24 -> 0.34828589 | H7: =Aux_Dashboard!$D$24 -> 11196 | K7: =Aux_Dashboard!$F$24 -> 88209.788
B9: =Aux_Dashboard!$B$27 -> 0.25963883 | E9: =Aux_Dashboard!$E$27*100 -> 0.41128992 | H9: =Aux_Dashboard!$D$27 -> 0.11325028 | K9: =Aux_Dashboard!$F$27 -> 0.13149653
B10: ="Variación "&Aux_Dashboard!$B$29&" · Período mostrado: "&Aux_Dashboard!$B$37&" (el % de margen se compara en puntos porcentuales)" -> Variación 2º semestre vs 1º semestre · Período mostrado: Total 2024 (el % de margen se compara en puntos porcentuales)
B11: Mes | E11: Región | H11: Categoría | K11: Estado del pedido
C12: (Todos) | F12: (Todos) | I12: (Todos) | L12: (Todos)
B13: Segmentadores: filtran los KPIs y los gráficos (cada gráfico no se filtra por su propia dimensión, para mantener visible la comparación). Elegí "(Todos)" para ver el total.
B15: =Aux_Dashboard!$B$32 -> Las ventas alcanzan su máximo en Julio | I15: =Aux_Dashboard!$B$33 -> La categoría Tecnología concentra la mayor venta del período
B32: =Aux_Dashboard!$B$34 -> La región Centro lidera las ventas del período | I32: Ventas vs. % de margen por producto (casos atípicos)
B48: Regiones ordenadas por ventas anuales. | I48: =Aux_Dashboard!$B$36 -> Mayor % de margen: Tablet 10 · Menor: Impresora
B50: NOTAS DE ANÁLISIS (cifras anuales 2024, sin filtros)
B51: 1) Tecnología concentra el 59% de las ventas netas 2024 ($586,1 M sobre $987,6 M); agrupa 6 de los 12 productos del catálogo.
B52: 2) El 2º semestre supera al 1º en un 26%, con picos en julio ($125,0 M) y diciembre ($115,4 M) y un mínimo en abril ($50,2 M).
B53: 3) Centro lidera las ventas por región (20% del total), mientras que Norte y CABA logran el mejor % de margen (≈39%).
B55: Limitaciones y lectura sugerida (revisión con IA – abogado del diablo):
B56: • Las cifras incluyen pedidos en todos los estados: los anulados y devueltos suman cerca del 26% del monto, por lo que la venta efectiva es menor. Usá el segmentador "Estado del pedido" (agregado a partir de esta revisión) para ver solo lo completado.
B57: • Hay un solo año de datos: el mayor nivel del 2º semestre puede responder a estacionalidad y no a una tendencia; no conviene extrapolarlo.
B58: • La participación por categoría y región no ajusta por cantidad de productos ni de operaciones: se recomienda leerla junto al detalle por producto.
B60: Nota técnica: los segmentadores están implementados como listas desplegables vinculadas a los cálculos (mismo criterio que el selector de mes del Dashboard original), conectadas a los 4 KPIs y a los 4 gráficos.

Sheet Dashboard
A1: Reporte de Ventas Trimestral
A2: =HYPERLINK("#Inicio_Dash","Resumen General") -> Resumen General | E2: =HYPERLINK("#Inicio_Detalle","Detalle por Producto") -> Detalle por Producto | J2: Ventas Netas
J3: =IF($B$3="",SUM(Datos_Crudos!$Q:$Q),SUMIFS(Datos_Crudos!$Q:$Q,Datos_Crudos!$C:$C,$B$3)) -> 9.8759678e+08
A5: =IF($B$3="","Reporte Anual Consolidado","Reporte Comparativo de Ventas: "&$B$3) -> Reporte Anual Consolidado
J6: =IFERROR((IF($B$3="",SUM(Datos_Crudos!$Q:$Q),SUMIFS(Datos_Crudos!$Q:$Q,Datos_Crudos!$C:$C,$B$3))/IF($B$3="",AVERAGE(Configuración!$B$4:$B$15),IF(MATCH($B$3,Configuración!$A$4:$A$15,0)=1,AVERAGE(Configuración!$B$4:$B$15),INDEX(Configuración!$B$4:$B$15,MATCH($B$3,Configuración!$A$4:$A$15,0)-1))))-1,0) -> 11
A26: El selector de mes funciona como sustituto práctico del segmentador para la práctica docente.

Sheet Detalle_Productos
A1: Detalle por Producto
A2: =HYPERLINK("#Inicio_Dash","Resumen General") -> Resumen General | E2: =HYPERLINK("#Inicio_Detalle","Detalle por Producto") -> Detalle por Producto
A5: Producto | B5: Categoría | C5: Unidades | D5: Ventas_Netas | E5: Margen | F5: Ticket_Promedio
A6: Notebook 14 | B6: Tecnología | C6: =SUMIFS(Datos_Crudos!$L:$L,Datos_Crudos!$H:$H,$A6) -> 522 | D6: =SUMIFS(Datos_Crudos!$Q:$Q,Datos_Crudos!$H:$H,$A6) -> 44641119 | E6: =SUMIFS(Datos_Crudos!$R:$R,Datos_Crudos!$H:$H,$A6) -> 13525265 | F6: =IFERROR($D6/$C6,0) -> 85519.384
A7: Mouse Inalámbrico | B7: Tecnología | C7: =SUMIFS(Datos_Crudos!$L:$L,Datos_Crudos!$H:$H,$A7) -> 896 | D7: =SUMIFS(Datos_Crudos!$Q:$Q,Datos_Crudos!$H:$H,$A7) -> 70563336 | E7: =SUMIFS(Datos_Crudos!$R:$R,Datos_Crudos!$H:$H,$A7) -> 22301135 | F7: =IFERROR($D7/$C7,0) -> 78753.723
A8: Teclado Mecánico | B8: Tecnología | C8: =SUMIFS(Datos_Crudos!$L:$L,Datos_Crudos!$H:$H,$A8) -> 1009 | D8: =SUMIFS(Datos_Crudos!$Q:$Q,Datos_Crudos!$H:$H,$A8) -> 1.1650021e+08 | E8: =SUMIFS(Datos_Crudos!$R:$R,Datos_Crudos!$H:$H,$A8) -> 42776574 | F8: =IFERROR($D8/$C8,0) -> 115461.06
A9: Monitor 24 | B9: Tecnología | C9: =SUMIFS(Datos_Crudos!$L:$L,Datos_Crudos!$H:$H,$A9) -> 1347 | D9: =SUMIFS(Datos_Crudos!$Q:$Q,Datos_Crudos!$H:$H,$A9) -> 1.3641004e+08 | E9: =SUMIFS(Datos_Crudos!$R:$R,Datos_Crudos!$H:$H,$A9) -> 48935363 | F9: =IFERROR($D9/$C9,0) -> 101269.52
A10: Silla Ergonómica | B10: Oficina | C10: =SUMIFS(Datos_Crudos!$L:$L,Datos_Crudos!$H:$H,$A10) -> 717 | D10: =SUMIFS(Datos_Crudos!$Q:$Q,Datos_Crudos!$H:$H,$A10) -> 56285393 | E10: =SUMIFS(Datos_Crudos!$R:$R,Datos_Crudos!$H:$H,$A10) -> 17910219 | F10: =IFERROR($D10/$C10,0) -> 78501.245
A11: Escritorio Compacto | B11: Oficina | C11: =SUMIFS(Datos_Crudos!$L:$L,Datos_Crudos!$H:$H,$A11) -> 783 | D11: =SUMIFS(Datos_Crudos!$Q:$Q,Datos_Crudos!$H:$H,$A11) -> 74942474 | E11: =SUMIFS(Datos_Crudos!$R:$R,Datos_Crudos!$H:$H,$A11) -> 26309456 | F11: =IFERROR($D11/$C11,0) -> 95711.972
A12: Lámpara LED | B12: Hogar | C12: =SUMIFS(Datos_Crudos!$L:$L,Datos_Crudos!$H:$H,$A12) -> 301 | D12: =SUMIFS(Datos_Crudos!$Q:$Q,Datos_Crudos!$H:$H,$A12) -> 20274678 | E12: =SUMIFS(Datos_Crudos!$R:$R,Datos_Crudos!$H:$H,$A12) -> 6055507.6 | F12: =IFERROR($D12/$C12,0) -> 67357.735
A13: Auriculares BT | B13: Tecnología | C13: =SUMIFS(Datos_Crudos!$L:$L,Datos_Crudos!$H:$H,$A13) -> 714 | D13: =SUMIFS(Datos_Crudos!$Q:$Q,Datos_Crudos!$H:$H,$A13) -> 53910056 | E13: =SUMIFS(Datos_Crudos!$R:$R,Datos_Crudos!$H:$H,$A13) -> 20843076 | F13: =IFERROR($D13/$C13,0) -> 75504.28
A14: Router WiFi | B14: Tecnología | C14: =SUMIFS(Datos_Crudos!$L:$L,Datos_Crudos!$H:$H,$A14) -> 955 | D14: =SUMIFS(Datos_Crudos!$Q:$Q,Datos_Crudos!$H:$H,$A14) -> 79120954 | E14: =SUMIFS(Datos_Crudos!$R:$R,Datos_Crudos!$H:$H,$A14) -> 23477805 | F14: =IFERROR($D14/$C14,0) -> 82849.166
A15: Cafetera | B15: Hogar | C15: =SUMIFS(Datos_Crudos!$L:$L,Datos_Crudos!$H:$H,$A15) -> 1744 | D15: =SUMIFS(Datos_Crudos!$Q:$Q,Datos_Crudos!$H:$H,$A15) -> 1.7418396e+08 | E15: =SUMIFS(Datos_Crudos!$R:$R,Datos_Crudos!$H:$H,$A15) -> 64604359 | F15: =IFERROR($D15/$C15,0) -> 99876.123
A16: Impresora | B16: Oficina | C16: =SUMIFS(Datos_Crudos!$L:$L,Datos_Crudos!$H:$H,$A16) -> 1367 | D16: =SUMIFS(Datos_Crudos!$Q:$Q,Datos_Crudos!$H:$H,$A16) -> 75854180 | E16: =SUMIFS(Datos_Crudos!$R:$R,Datos_Crudos!$H:$H,$A16) -> 22122417 | F16: =IFERROR($D16/$C16,0) -> 55489.524
A17: Tablet 10 | B17: Tecnología | C17: =SUMIFS(Datos_Crudos!$L:$L,Datos_Crudos!$H:$H,$A17) -> 841 | D17: =SUMIFS(Datos_Crudos!$Q:$Q,Datos_Crudos!$H:$H,$A17) -> 84910390 | E17: =SUMIFS(Datos_Crudos!$R:$R,Datos_Crudos!$H:$H,$A17) -> 35104848 | F17: =IFERROR($D17/$C17,0) -> 100963.6
A20: Sugerencia docente: pedir al estudiante que clasifique categorías inconsistentes y compare un producto contra el promedio del mes.

Sheet Configuración
A1: Configuración y Resumen Mensual
A3: Mes | B3: Ventas_Netas | C3: Margen | D3: Unidades | E3: Ticket_Promedio | G3: Paleta sugerida
A4: Enero | B4: =SUMIFS(Datos_Crudos!$Q:$Q,Datos_Crudos!$C:$C,$A4) -> 74587318 | C4: =SUMIFS(Datos_Crudos!$R:$R,Datos_Crudos!$C:$C,$A4) -> 25491254 | D4: =SUMIFS(Datos_Crudos!$L:$L,Datos_Crudos!$C:$C,$A4) -> 735 | E4: =IFERROR($B4/$D4,0) -> 101479.34 | G4: Primario | H4: #0F766E
A5: Febrero | B5: =SUMIFS(Datos_Crudos!$Q:$Q,Datos_Crudos!$C:$C,$A5) -> 59788146 | C5: =SUMIFS(Datos_Crudos!$R:$R,Datos_Crudos!$C:$C,$A5) -> 16555685 | D5: =SUMIFS(Datos_Crudos!$L:$L,Datos_Crudos!$C:$C,$A5) -> 961 | E5: =IFERROR($B5/$D5,0) -> 62214.512 | G5: Secundario | H5: #2563EB
A6: Marzo | B6: =SUMIFS(Datos_Crudos!$Q:$Q,Datos_Crudos!$C:$C,$A6) -> 95487410 | C6: =SUMIFS(Datos_Crudos!$R:$R,Datos_Crudos!$C:$C,$A6) -> 36813684 | D6: =SUMIFS(Datos_Crudos!$L:$L,Datos_Crudos!$C:$C,$A6) -> 1122 | E6: =IFERROR($B6/$D6,0) -> 85104.644 | G6: Acento | H6: #F59E0B
A7: Abril | B7: =SUMIFS(Datos_Crudos!$Q:$Q,Datos_Crudos!$C:$C,$A7) -> 50180273 | C7: =SUMIFS(Datos_Crudos!$R:$R,Datos_Crudos!$C:$C,$A7) -> 15001026 | D7: =SUMIFS(Datos_Crudos!$L:$L,Datos_Crudos!$C:$C,$A7) -> 564 | E7: =IFERROR($B7/$D7,0) -> 88972.116 | G7: Grises | H7: #6B7280 / #E5E7EB
A8: Mayo | B8: =SUMIFS(Datos_Crudos!$Q:$Q,Datos_Crudos!$C:$C,$A8) -> 63280396 | C8: =SUMIFS(Datos_Crudos!$R:$R,Datos_Crudos!$C:$C,$A8) -> 23107822 | D8: =SUMIFS(Datos_Crudos!$L:$L,Datos_Crudos!$C:$C,$A8) -> 804 | E8: =IFERROR($B8/$D8,0) -> 78706.96 | G8: Nota | H8: Usar Mes como lista para el selector del dashboard.
A9: Junio | B9: =SUMIFS(Datos_Crudos!$Q:$Q,Datos_Crudos!$C:$C,$A9) -> 93736031 | C9: =SUMIFS(Datos_Crudos!$R:$R,Datos_Crudos!$C:$C,$A9) -> 34250147 | D9: =SUMIFS(Datos_Crudos!$L:$L,Datos_Crudos!$C:$C,$A9) -> 1112 | E9: =IFERROR($B9/$D9,0) -> 84294.992
A10: Julio | B10: =SUMIFS(Datos_Crudos!$Q:$Q,Datos_Crudos!$C:$C,$A10) -> 1.2501894e+08 | C10: =SUMIFS(Datos_Crudos!$R:$R,Datos_Crudos!$C:$C,$A10) -> 45527917 | D10: =SUMIFS(Datos_Crudos!$L:$L,Datos_Crudos!$C:$C,$A10) -> 1376 | E10: =IFERROR($B10/$D10,0) -> 90856.791 | G10: Selector sugerido | H10: B3 en Dashboard
A11: Agosto | B11: =SUMIFS(Datos_Crudos!$Q:$Q,Datos_Crudos!$C:$C,$A11) -> 62673741 | C11: =SUMIFS(Datos_Crudos!$R:$R,Datos_Crudos!$C:$C,$A11) -> 19261078 | D11: =SUMIFS(Datos_Crudos!$L:$L,Datos_Crudos!$C:$C,$A11) -> 668 | E11: =IFERROR($B11/$D11,0) -> 93822.965 | G11: Comparativo | H11: Variación vs referencia
A12: Septiembre | B12: =SUMIFS(Datos_Crudos!$Q:$Q,Datos_Crudos!$C:$C,$A12) -> 59677427 | C12: =SUMIFS(Datos_Crudos!$R:$R,Datos_Crudos!$C:$C,$A12) -> 16746029 | D12: =SUMIFS(Datos_Crudos!$L:$L,Datos_Crudos!$C:$C,$A12) -> 675 | E12: =IFERROR($B12/$D12,0) -> 88411.003 | G12: Impresión | H12: Horizontal / una página de ancho
A13: Octubre | B13: =SUMIFS(Datos_Crudos!$Q:$Q,Datos_Crudos!$C:$C,$A13) -> 86928102 | C13: =SUMIFS(Datos_Crudos!$R:$R,Datos_Crudos!$C:$C,$A13) -> 26810874 | D13: =SUMIFS(Datos_Crudos!$L:$L,Datos_Crudos!$C:$C,$A13) -> 763 | E13: =IFERROR($B13/$D13,0) -> 113929.36
A14: Noviembre | B14: =SUMIFS(Datos_Crudos!$Q:$Q,Datos_Crudos!$C:$C,$A14) -> 1.0078942e+08 | C14: =SUMIFS(Datos_Crudos!$R:$R,Datos_Crudos!$C:$C,$A14) -> 36077855 | D14: =SUMIFS(Datos_Crudos!$L:$L,Datos_Crudos!$C:$C,$A14) -> 1297 | E14: =IFERROR($B14/$D14,0) -> 77709.65
A15: Diciembre | B15: =SUMIFS(Datos_Crudos!$Q:$Q,Datos_Crudos!$C:$C,$A15) -> 1.1544958e+08 | C15: =SUMIFS(Datos_Crudos!$R:$R,Datos_Crudos!$C:$C,$A15) -> 48322654 | D15: =SUMIFS(Datos_Crudos!$L:$L,Datos_Crudos!$C:$C,$A15) -> 1119 | E15: =IFERROR($B15/$D15,0) -> 103172.1

Sheet Datos_Crudos
A1: Fecha | B1: Año | C1: Mes | D1: Trimestre | E1: Región | F1: Canal | G1: Cliente | H1: Producto | I1: Categoría | J1: Subcategoría | K1: Vendedor | L1: Unidades | M1: Precio_Lista | N1: Descuento_% | O1: Costo_Unitario | P1: Ventas_Brutas | Q1: Ventas_Netas | R1: Margen | S1: Estado_Pedido
A2: 45295 | B2: 2024 | C2: Enero | D2: Q1 | E2: Norte | F2: market place | G2: Cliente 032 | H2: Impresora | I2: OFICINA | J2: Periféricos | K2: Juan Pérez | L2: 9 | M2: 154964 | N2: 0.08 | O2: 71457.61 | P2: 1394676 | Q2: 1283101.9 | R2: 639983.43 | S2: Completado
A3: 45340 | B3: 2024 | C3: Febrero | D3: Q1 | E3: CABA | F3: Ecommerce | G3: Cliente 036 | H3: Tablet 10 | I3: tecnologia | J3: Movilidad | K3: Nicolás Ríos | L3: 1 | M3: 53853 | O3: 29471.32 | P3: 53853 | Q3: 53853 | R3: 24381.68 | S3: Pendiente
A4: 45360 | B4: 2024 | C4: Marzo | D4: Q1 | E4: Patagonia | F4: ONLINE | G4: Cliente 059 | H4: Cafetera | I4: HOGAR | J4: Electrodomésticos | K4: Pedro Díaz | L4: 8 | M4: 111230 | N4: 0.2 | O4: 82342.64 | P4: 889840 | Q4: 711872 | R4: 53130.88 | S4: completado
A5: 45407 | B5: 2024 | C5: Abril | D5: Q2 | E5: Centro | F5: Online | G5: Cliente 013 | H5: Monitor 24 | I5: TECNOLOGÍA | J5: Imagen | K5: Luis Gómez | L5: 18 | M5: 107638 | O5: 56329.92 | P5: 1937484 | Q5: 1937484 | R5: 923545.44 | S5: Devuelto
A6: 45420 | B6: 2024 | C6: Mayo | D6: Q2 | E6: Sur | F6: mayorista | G6: Cliente 035 | H6: Tablet 10 | I6: TECNOLOGÍA | J6: Movilidad | K6: Marta Ruiz | L6: 36 | M6: 97008 | N6: 0 | O6: 51430.42 | P6: 3492288 | Q6: 3492288 | R6: 1640792.9 | S6: Completado
A7: 45454 | B7: 2024 | C7: Junio | D7: Q2 | E7: Sur | F7: market place | G7: Cliente 051 | H7: Tablet 10 | I7: TECNOLOGÍA | J7: Movilidad | K7: Marta Ruiz | L7: 30 | M7: 48603 | N7: 0.2 | O7: 34578.84 | P7: 1458090 | Q7: 1166472 | R7: 129106.8 | S7: Anulado
A8: 45476 | B8: 2024 | C8: Julio | D8: Q3 | E8: Patagonia | F8: Online | G8: Cliente 020 | H8: Auriculares BT | I8: TECNOLOGÍA | J8: Audio | K8: Marta Ruiz | L8: 11 | M8: 122666 | O8: 71583.8 | P8: 1349326 | Q8: 1241379.9 | R8: 453958.12 | S8: Anulado
A9: 45526 | B9: 2024 | C9: Agosto | D9: Q3 | E9: Interior | F9: RETAIL | G9: Cliente 015 | H9: Mouse Inalámbrico | I9: TECNOLOGÍA | J9: Accesorios | K9: Sofía García | L9: 28 | M9: 12850 | N9: 0.2 | O9: 10153.57 | P9: 359800 | Q9: 287840 | R9: 3540.04 | S9: Pendiente
A10: 45542 | B10: 2024 | C10: Septiembre | D10: Q3 | E10: Sur | F10: Retail | G10: Cliente 070 | H10: Cafetera | I10: HOGAR | J10: Electrodomésticos | K10: Nicolás Ríos | L10: 34 | M10: 169009 | N10: 0 | O10: 82671.38 | P10: 5746306 | Q10: 5746306 | R10: 2935479.1 | S10: Devuelto
A11: 45568 | B11: 2024 | C11: Octubre | D11: Q4 | E11: Costa | F11: Mayorista | G11: Cliente 069 | H11: Mouse Inalámbrico | I11: Tecnología | J11: Accesorios | K11: Nicolás Ríos | L11: 9 | M11: 136592 | N11: 0.1 | O11: 74138.02 | P11: 1229328 | Q11: 1106395.2 | R11: 439153.02 | S11: completado
A12: 45606 | B12: 2024 | C12: Noviembre | D12: Q4 | E12: CABA | F12: MARKETPLACE | G12: Cliente 048 | H12: Tablet 10 | I12: Tecnología | J12: Movilidad | K12: Luis Gómez | L12: 34 | M12: 76986 | O12: 35210.47 | P12: 2617524 | Q12: 2617524 | R12: 1420368 | S12: completado
A13: 45628 | B13: 2024 | C13: Diciembre | D13: Q4 | E13: Patagonia | F13: Retail | G13: Cliente 066 | H13: Mouse Inalámbrico | I13: tecnologia | J13: Accesorios | K13: Juan Pérez | L13: 18 | M13: 68160 | N13: 0.12 | O13: 36468.94 | P13: 1226880 | Q13: 1079654.4 | R13: 423213.48 | S13: Anulado
A14: 45306 | B14: 2024 | C14: Enero | D14: Q1 | E14: Patagonia | F14: Marketplace | G14: Cliente 013 | H14: Lámpara LED | I14: hogar | J14: Iluminación | K14: Ana López | L14: 26 | M14: 40644 | N14: 0.15 | O14: 25918.68 | P14: 1056744 | Q14: 898232.4 | R14: 224346.72 | S14: Pendiente
A15: 45326 | B15: 2024 | C15: Febrero | D15: Q1 | E15: Norte | F15: MARKETPLACE | G15: Cliente 002 | H15: Router WiFi | I15: tecnologia | J15: Redes | K15: Ana López | L15: 16 | M15: 139307 | N15: 0.08 | O15: 106688.96 | P15: 2228912 | Q15: 2050599 | R15: 343575.68 | S15: Pendiente
A16: 45365 | B16: 2024 | C16: Marzo | D16: Q1 | E16: Costa | F16: MARKETPLACE | G16: Cliente 063 | H16: Silla Ergonómica | I16: Oficina | J16: Mobiliario | K16: Juan Pérez | L16: 13 | M16: 27331 | N16: 0 | O16: 19453.97 | P16: 355303 | Q16: 355303 | R16: 102401.39 | S16: Completado
A17: 45385 | B17: 2024 | C17: Abril | D17: Q2 | E17: Patagonia | F17: E-commerce | G17: Cliente 009 | H17: Router WiFi | I17: TECNOLOGÍA | J17: Redes | K17: Marta Ruiz | L17: 16 | M17: 161336 | N17: 0 | O17: 107576.19 | P17: 2581376 | Q17: 2581376 | R17: 860156.96 | S17: Anulado
A18: 45423 | B18: 2024 | C18: Mayo | D18: Q2 | E18: Sur | F18: RETAIL | G18: Cliente 017 | H18: Tablet 10 | I18: Tecnología | J18: Movilidad | K18: Marta Ruiz | L18: 20 | M18: 124064 | N18: 0.05 | O18: 59009.96 | P18: 2481280 | Q18: 2357216 | R18: 1177016.8 | S18: Pendiente
A19: 45453 | B19: 2024 | C19: Junio | D19: Q2 | E19: Sur | F19: mayorista | G19: Cliente 068 | H19: Escritorio Compacto | I19: oficina | J19: Mobiliario | K19: Ana López | L19: 36 | M19: 39154 | N19: 0.1 | O19: 21243.51 | P19: 1409544 | Q19: 1268589.6 | R19: 503823.24 | S19: Completado
A20: 45495 | B20: 2024 | C20: Julio | D20: Q3 | E20: Costa | F20: RETAIL | G20: Cliente 033 | H20: Monitor 24 | I20: tecnologia | J20: Imagen | K20: Nicolás Ríos | L20: 4 | M20: 123037 | N20: 0 | O20: 55519.34 | P20: 492148 | Q20: 492148 | R20: 270070.64 | S20: Pendiente
A21: 45505 | B21: 2024 | C21: Agosto | D21: Q3 | E21: Norte | F21: ONLINE | G21: Cliente 020 | H21: Router WiFi | I21: tecnologia | J21: Redes | K21: Pedro Díaz | L21: 3 | M21: 164701 | N21: 0.08 | O21: 81462.09 | P21: 494103 | Q21: 454574.76 | R21: 210188.49 | S21: Devuelto
A22: 45557 | B22: 2024 | C22: Septiembre | D22: Q3 | E22: Sur | F22: Marketplace | G22: Cliente 046 | H22: Monitor 24 | I22: Tecnología | J22: Imagen | K22: Nicolás Ríos | L22: 36 | M22: 118529 | N22: 0.1 | O22: 91743.5 | P22: 4267044 | Q22: 3840339.6 | R22: 537573.6 | S22: Pendiente
A23: 45589 | B23: 2024 | C23: Octubre | D23: Q4 | E23: Centro | F23: Mayorista | G23: Cliente 035 | H23: Teclado Mecánico | I23: TECNOLOGÍA | J23: Accesorios | K23: Juan Pérez | L23: 7 | M23: 22151 | N23: 0.15 | O23: 11515.21 | P23: 155057 | Q23: 131798.45 | R23: 51191.98 | S23: Anulado
A24: 45609 | B24: 2024 | C24: Noviembre | D24: Q4 | E24: Centro | F24: Retail | G24: Cliente 036 | H24: Monitor 24 | I24: tecnologia | J24: Imagen | K24: Sofía García | L24: 33 | M24: 152565 | N24: 0 | O24: 74813.24 | P24: 5034645 | Q24: 5034645 | R24: 2565808.1 | S24: Devuelto
... A26: 45313 | B26: 2024 | C26: Enero | D26: Q1 | E26: Centro | F26: Distribuidor | G26: Cliente 016 | H26: Mouse Inalámbrico | I26: TECNOLOGÍA | J26: Accesorios | K26: Marta Ruiz | L26: 20 | M26: 119057 | N26: 0.2 | O26: 76677.99 | P26: 2381140 | Q26: 1904912 | R26: 371352.2 | S26: Pendiente
A27: 45332 | B27: 2024 | C27: Febrero | D27: Q1 | E27: CABA | F27: Distribuidor | G27: Cliente 039 | H27: Cafetera | I27: HOGAR | J27: Electrodomésticos | K27: Sofía García | L27: 14 | M27: 164039 | O27: 100514.22 | P27: 2296546 | Q27: 2296546 | R27: 889346.92 | S27: Anulado
A28: 45373 | B28: 2024 | C28: Marzo | D28: Q1 | E28: Norte | F28: RETAIL | G28: Cliente 012 | H28: Teclado Mecánico | I28: TECNOLOGÍA | J28: Accesorios | K28: Nicolás Ríos | L28: 16 | M28: 70888 | N28: 0.1 | O28: 32505.61 | P28: 1134208 | Q28: 1020787.2 | R28: 500697.44 | S28: Pendiente
A29: 45389 | B29: 2024 | C29: Abril | D29: Q2 | E29: Costa | F29: market place | G29: Cliente 064 | H29: Cafetera | I29: Hogar | J29: Electrodomésticos | K29: Luis Gómez | L29: 16 | M29: 13453 | N29: 0.05 | O29: 9719.08 | P29: 215248 | Q29: 204485.6 | R29: 48980.32 | S29: Pendiente
A30: 45427 | B30: 2024 | C30: Mayo | D30: Q2 | E30: Sur | F30: mayorista | G30: Cliente 057 | H30: Mouse Inalámbrico | I30: TECNOLOGÍA | J30: Accesorios | K30: Pedro Díaz | L30: 33 | M30: 155621 | N30: 0.1 | O30: 110534.39 | P30: 5135493 | Q30: 4621943.7 | R30: 974308.83 | S30: Anulado
A31: 45464 | B31: 2024 | C31: Junio | D31: Q2 | E31: Sur | F31: RETAIL | G31: Cliente 010 | H31: Auriculares BT | I31: tecnologia | J31: Audio | K31: Marta Ruiz | L31: 19 | M31: 100040 | N31: 0.05 | O31: 49863.03 | P31: 1900760 | Q31: 1805722 | R31: 858324.43 | S31: Pendiente
A32: 45488 | B32: 2024 | C32: Julio | D32: Q3 | E32: CABA | F32: Online | G32: Cliente 054 | H32: Router WiFi | I32: TECNOLOGÍA | J32: Redes | K32: Luis Gómez | L32: 38 | M32: 17120 | N32: 0.08 | O32: 10562.06 | P32: 650560 | Q32: 598515.2 | R32: 197156.92 | S32: Devuelto
A33: 45528 | B33: 2024 | C33: Agosto | D33: Q3 | E33: Interior | F33: Distribuidor | G33: Cliente 063 | H33: Tablet 10 | I33: TECNOLOGÍA | J33: Movilidad | K33: Juan Pérez | L33: 18 | M33: 19608 | N33: 0.08 | O33: 13793.51 | P33: 352944 | Q33: 324708.48 | R33: 76425.3 | S33: Anulado
A34: 45557 | B34: 2024 | C34: Septiembre | D34: Q3 | E34: Norte | F34: ONLINE | G34: Cliente 055 | H34: Cafetera | I34: hogar | J34: Electrodomésticos | K34: Juan Pérez | L34: 30 | M34: 80198 | N34: 0.15 | O34: 48852.19 | P34: 2405940 | Q34: 2045049 | R34: 579483.3 | S34: Devuelto
A35: 45581 | B35: 2024 | C35: Octubre | D35: Q4 | E35: Norte | F35: MARKETPLACE | G35: Cliente 007 | H35: Mouse Inalámbrico | I35: Tecnología | J35: Accesorios | K35: Sofía García | L35: 15 | M35: 22553 | N35: 0.15 | O35: 11722.51 | P35: 338295 | Q35: 287550.75 | R35: 111713.1 | S35: Completado
A36: 45619 | B36: 2024 | C36: Noviembre | D36: Q4 | E36: Centro | F36: Retail | G36: Cliente 015 | H36: Auriculares BT | I36: TECNOLOGÍA | J36: Audio | K36: Nicolás Ríos | L36: 11 | M36: 40337 | N36: 0.2 | O36: 26280.72 | P36: 443707 | Q36: 354965.6 | R36: 65877.68 | S36: Anulado
A37: 45630 | B37: 2024 | C37: Diciembre | D37: Q4 | E37: Costa | F37: Retail | G37: Cliente 006 | H37: Monitor 24 | I37: tecnologia | J37: Imagen | K37: Sofía García | L37: 35 | M37: 109142 | O37: 49597.21 | P37: 3819970 | Q37: 3819970 | R37: 2084067.6 | S37: Anulado
A38: 45296 | B38: 2024 | C38: Enero | D38: Q1 | E38: CABA | F38: ecommerce | G38: Cliente 067 | H38: Tablet 10 | I38: tecnologia | J38: Movilidad | K38: Marta Ruiz | L38: 18 | M38: 153078 | N38: 0.12 | O38: 92222.01 | P38: 2755404 | Q38: 2424755.5 | R38: 764759.34 | S38: COMPLETADO
A39: 45330 | B39: 2024 | C39: Febrero | D39: Q1 | E39: Patagonia | F39: mayorista | G39: Cliente 044 | H39: Auriculares BT | I39: TECNOLOGÍA | J39: Audio | K39: Ana López | L39: 32 | M39: 59668 | O39: 43512.37 | P39: 1909376 | Q39: 1909376 | R39: 516980.16 | S39: Devuelto
A40: 45354 | B40: 2024 | C40: Marzo | D40: Q1 | E40: Sur | F40: market place | G40: Cliente 063 | H40: Monitor 24 | I40: TECNOLOGÍA | J40: Imagen | K40: Pedro Díaz | L40: 16 | M40: 140665 | N40: 0 | O40: 67880.52 | P40: 2250640 | Q40: 2250640 | R40: 1164551.7 | S40: Pendiente
A41: 45394 | B41: 2024 | C41: Abril | D41: Q2 | E41: CABA | F41: MARKETPLACE | G41: Cliente 043 | H41: Router WiFi | I41: tecnologia | J41: Redes | K41: Sofía García | L41: 30 | M41: 77903 | N41: 0.15 | O41: 43660.1 | P41: 2337090 | Q41: 1986526.5 | R41: 676723.5 | S41: COMPLETADO
A42: 45436 | B42: 2024 | C42: Mayo | D42: Q2 | E42: Interior | F42: Distribuidor | G42: Cliente 013 | H42: Silla Ergonómica | I42: Oficina | J42: Mobiliario | K42: Nicolás Ríos | L42: 13 | M42: 106602 | N42: 0 | O42: 74387.57 | P42: 1385826 | Q42: 1385826 | R42: 418787.59 | S42: Pendiente
A43: 45471 | B43: 2024 | C43: Junio | D43: Q2 | E43: Patagonia | F43: Mayorista | G43: Cliente 002 | H43: Impresora | I43: OFICINA | J43: Periféricos | K43: Pedro Díaz | L43: 19 | M43: 127466 | N43: 0 | O43: 68623.54 | P43: 2421854 | Q43: 2421854 | R43: 1118006.7 | S43: Anulado
A44: 45478 | B44: 2024 | C44: Julio | D44: Q3 | E44: Sur | F44: Distribuidor | G44: Cliente 011 | H44: Notebook 14 | I44: tecnologia | J44: Computación | K44: Juan Pérez | L44: 8 | M44: 121097 | N44: 0.15 | O44: 87370.61 | P44: 968776 | Q44: 823459.6 | R44: 124494.72 | S44: Anulado
A45: 45524 | B45: 2024 | C45: Agosto | D45: Q3 | E45: Norte | F45: Distribuidor | H45: Cafetera | I45: Hogar | J45: Electrodomésticos | K45: Marta Ruiz | L45: 14 | M45: 33282 | N45: 0.1 | O45: 21406.89 | P45: 465948 | Q45: 419353.2 | R45: 119656.74 | S45: Pendiente
A46: 45558 | B46: 2024 | C46: Septiembre | D46: Q3 | E46: Centro | F46: market place | G46: Cliente 010 | H46: Silla Ergonómica | I46: Oficina | J46: Mobiliario | K46: Marta Ruiz | L46: 15 | M46: 175855 | N46: 0.15 | O46: 105301.73 | P46: 2637825 | Q46: 2242151.2 | R46: 662625.3 | S46: completado
A47: 45591 | B47: 2024 | C47: Octubre | D47: Q4 | E47: Centro | F47: Distribuidor | H47: Teclado Mecánico | I47: Tecnología | J47: Accesorios | K47: Ana López | L47: 30 | M47: 117515 | N47: 0.12 | O47: 70886.88 | P47: 3525450 | Q47: 3102396 | R47: 975789.6 | S47: completado
A48: 45618 | B48: 2024 | C48: Noviembre | D48: Q4 | E48: Patagonia | F48: Distribuidor | G48: Cliente 035 | H48: Monitor 24 | I48: tecnologia | J48: Imagen | K48: Pedro Díaz | L48: 3 | M48: 57925 | N48: 0.12 | O48: 44638.48 | P48: 173775 | Q48: 152922 | R48: 19006.56 | S48: Pendiente
A49: 45640 | B49: 2024 | C49: Diciembre | D49: Q4 | E49: Centro | F49: Retail | H49: Escritorio Compacto | I49: oficina | J49: Mobiliario | K49: Sofía García | L49: 27 | M49: 87554 | N49: 0.08 | O49: 64330.14 | P49: 2363958 | Q49: 2174841.4 | R49: 437927.58 | S49: completado
A50: 45318 | B50: 2024 | C50: Enero | D50: Q1 | E50: Norte | F50: MARKETPLACE | G50: Cliente 060 | H50: Router WiFi | I50: TECNOLOGÍA | J50: Redes | K50: Luis Gómez | L50: 4 | M50: 106838 | N50: 0.12 | O50: 71463.2 | P50: 427352 | Q50: 376069.76 | R50: 90216.96 | S50: Completado
A51: 45326 | B51: 2024 | C51: Febrero | D51: Q1 | E51: Norte | F51: MARKETPLACE | G51: Cliente 031 | H51: Auriculares BT | I51: TECNOLOGÍA | J51: Audio | K51: Marta Ruiz | L51: 11 | M51: 15584 | N51: 0.05 | O51: 8238.41 | P51: 171424 | Q51: 162852.8 | R51: 72230.29 | S51: Completado
A52: 45368 | B52: 2024 | C52: Marzo | D52: Q1 | E52: Costa | F52: RETAIL | G52: Cliente 062 | H52: Silla Ergonómica | I52: oficina | J52: Mobiliario | K52: Luis Gómez | L52: 16 | M52: 49917 | N52: 0.1 | O52: 37558.02 | P52: 798672 | Q52: 718804.8 | R52: 117876.48 | S52: Devuelto
A53: 45392 | B53: 2024 | C53: Abril | D53: Q2 | E53: Costa | F53: RETAIL | G53: Cliente 020 | H53: Notebook 14 | I53: tecnologia | J53: Computación | K53: Luis Gómez | L53: 35 | M53: 99147 | N53: 0.08 | O53: 60417.27 | P53: 3470145 | Q53: 3192533.4 | R53: 1077928.9 | S53: Devuelto
A54: 45423 | B54: 2024 | C54: Mayo | D54: Q2 | E54: Costa | F54: mayorista | G54: Cliente 050 | H54: Notebook 14 | I54: TECNOLOGÍA | J54: Computación | K54: Marta Ruiz | L54: 10 | M54: 21704 | O54: 16373.39 | P54: 217040 | R54: 53306.1 | S54: Anulado
A55: 45446 | B55: 2024 | C55: Junio | D55: Q2 | E55: CABA | F55: RETAIL | G55: Cliente 051 | H55: Teclado Mecánico | I55: tecnologia | J55: Accesorios | K55: Marta Ruiz | L55: 6 | M55: 151885 | O55: 101668.74 | P55: 911310 | Q55: 911310 | R55: 301297.56 | S55: Anulado
A56: 45497 | B56: 2024 | C56: Julio | D56: Q3 | E56: Norte | F56: Mayorista | G56: Cliente 013 | H56: Monitor 24 | I56: Tecnología | J56: Imagen | K56: Luis Gómez | L56: 11 | M56: 19588 | N56: 0 | O56: 10825.87 | P56: 215468 | Q56: 215468 | R56: 96383.43 | S56: Devuelto
A57: 45510 | B57: 2024 | C57: Agosto | D57: Q3 | E57: Norte | F57: Distribuidor | G57: Cliente 031 | H57: Teclado Mecánico | I57: Tecnología | J57: Accesorios | K57: Luis Gómez | L57: 38 | M57: 132887 | N57: 0.12 | O57: 71674.51 | P57: 5049706 | Q57: 4443741.3 | R57: 1720109.9 | S57: Completado
A58: 45547 | B58: 2024 | C58: Septiembre | D58: Q3 | E58: Interior | F58: RETAIL | G58: Cliente 033 | H58: Auriculares BT | I58: TECNOLOGÍA | J58: Audio | K58: Luis Gómez | L58: 20 | M58: 112845 | N58: 0.05 | O58: 60148.87 | P58: 2256900 | Q58: 2144055 | R58: 941077.6 | S58: completado
A59: 45574 | B59: 2024 | C59: Octubre | D59: Q4 | E59: Norte | F59: Distribuidor | G59: Cliente 064 | H59: Lámpara LED | I59: Hogar | J59: Iluminación | K59: Nicolás Ríos | L59: 19 | M59: 72324 | O59: 38089.55 | P59: 1374156 | Q59: 1374156 | R59: 650454.55 | S59: Pendiente
A60: 45600 | B60: 2024 | C60: Noviembre | D60: Q4 | E60: Costa | F60: Marketplace | G60: Cliente 040 | H60: Impresora | I60: OFICINA | J60: Periféricos | K60: Nicolás Ríos | L60: 290 | M60: 46448 | N60: 0.2 | O60: 26213.01 | P60: 13469920 | Q60: 10775936 | R60: 3174163.1 | S60: Anulado
A61: 45635 | B61: 2024 | C61: Diciembre | D61: Q4 | E61: Patagonia | F61: Ecommerce | G61: Cliente 062 | H61: Router WiFi | I61: tecnologia | J61: Redes | K61: Nicolás Ríos | L61: 19 | M61: 100792 | N61: 0.12 | O61: 79324.58 | P61: 1915048 | Q61: 1685242.2 | R61: 178075.22 | S61: Pendiente
A62: 45303 | B62: 2024 | C62: Enero | D62: Q1 | E62: Norte | F62: Mayorista | G62: Cliente 034 | H62: Router WiFi | I62: TECNOLOGÍA | J62: Redes | K62: Pedro Díaz | L62: 8 | M62: 80724 | O62: 39386.95 | P62: 645792 | Q62: 645792 | R62: 330696.4 | S62: Pendiente
A63: 45343 | B63: 2024 | C63: Febrero | D63: Q1 | E63: Norte | F63: market place | G63: Cliente 039 | H63: Monitor 24 | I63: TECNOLOGÍA | J63: Imagen | K63: Marta Ruiz | L63: 27 | M63: 23887 | N63: 0.2 | O63: 19075.55 | P63: 644949 | Q63: 515959.2 | R63: 919.35 | S63: Completado
A64: 45374 | B64: 2024 | C64: Marzo | D64: Q1 | E64: Interior | F64: Mayorista | G64: Cliente 054 | H64: Tablet 10 | I64: TECNOLOGÍA | J64: Movilidad | K64: Marta Ruiz | L64: 7 | M64: 173389 | N64: 0.2 | O64: 80010.48 | P64: 1213723 | Q64: 970978.4 | R64: 410905.04 | S64: Devuelto
A65: 45400 | B65: 2024 | C65: Abril | D65: Q2 | E65: Costa | F65: Retail | G65: Cliente 051 | H65: Escritorio Compacto | I65: OFICINA | J65: Mobiliario | K65: Sofía García | L65: 13 | M65: 131201 | N65: 0.15 | O65: 88507.74 | P65: 1705613 | Q65: 1449771.1 | R65: 299170.43 | S65: completado
A66: 45415 | B66: 2024 | C66: Mayo | D66: Q2 | E66: Patagonia | F66: Distribuidor | G66: Cliente 028 | H66: Monitor 24 | I66: Tecnología | J66: Imagen | K66: Nicolás Ríos | L66: 15 | M66: 50680 | N66: 0 | O66: 27724.3 | P66: 760200 | Q66: 760200 | R66: 344335.5 | S66: Pendiente
A67: 45444 | B67: 2024 | C67: Junio | D67: Q2 | E67: Centro | F67: ecommerce | G67: Cliente 042 | H67: Teclado Mecánico | I67: Tecnología | J67: Accesorios | K67: Ana López | L67: 12 | M67: 45228 | N67: 0.05 | O67: 32156.33 | P67: 542736 | Q67: 515599.2 | R67: 129723.24 | S67: Anulado
A68: 45475 | B68: 2024 | C68: Julio | D68: Q3 | E68: Costa | F68: MARKETPLACE | G68: Cliente 039 | H68: Cafetera | I68: Hogar | J68: Electrodomésticos | K68: Luis Gómez | L68: 2 | M68: 137562 | N68: 0.08 | O68: 94936.23 | P68: 275124 | Q68: 253114.08 | R68: 63241.62 | S68: Anulado
A69: 45509 | B69: 2024 | C69: Agosto | D69: Q3 | E69: Centro | F69: Distribuidor | G69: Cliente 049 | H69: Mouse Inalámbrico | I69: Tecnología | J69: Accesorios | K69: Pedro Díaz | L69: 34 | M69: 144527 | N69: 0.05 | O69: 105155.48 | P69: 4913918 | Q69: 4668222.1 | R69: 1092935.8 | S69: Completado
A70: 45550 | B70: 2024 | C70: Septiembre | D70: Q3 | E70: Sur | F70: mayorista | G70: Cliente 059 | H70: Lámpara LED | I70: hogar | J70: Iluminación | K70: Luis Gómez | L70: 27 | M70: 93932 | N70: 0.2 | O70: 54575 | P70: 2536164 | Q70: 2028931.2 | R70: 555406.2 | S70: Pendiente
A71: 45589 | B71: 2024 | C71: Octubre | D71: Q4 | E71: Costa | F71: Retail | G71: Cliente 008 | H71: Mouse Inalámbrico | I71: TECNOLOGÍA | J71: Accesorios | K71: Pedro Díaz | L71: 36 | M71: 44042 | N71: 0.08 | O71: 33200.28 | P71: 1585512 | Q71: 1458671 | R71: 263460.96 | S71: COMPLETADO
A72: 45601 | B72: 2024 | C72: Noviembre | D72: Q4 | E72: Costa | F72: Mayorista | G72: Cliente 014 | H72: Monitor 24 | I72: TECNOLOGÍA | J72: Imagen | K72: Sofía García | L72: 36 | M72: 85024 | N72: 0.08 | O72: 63411.27 | P72: 3060864 | Q72: 2815994.9 | R72: 533189.16 | S72: completado
A73: 45627 | B73: 2024 | C73: Diciembre | D73: Q4 | E73: Sur | F73: RETAIL | G73: Cliente 044 | H73: Silla Ergonómica | I73: oficina | J73: Mobiliario | K73: Sofía García | L73: 1 | M73: 49552 | N73: 0.08 | O73: 23505.23 | P73: 49552 | Q73: 45587.84 | R73: 22082.61 | S73: COMPLETADO
A74: 45302 | B74: 2024 | C74: Enero | D74: Q1 | E74: Sur | F74: RETAIL | G74: Cliente 042 | H74: Auriculares BT | I74: Tecnología | J74: Audio | K74: Nicolás Ríos | L74: 37 | M74: 25791 | N74: 0 | O74: 17689.76 | P74: 954267 | Q74: 954267 | R74: 299745.88 | S74: Devuelto
A75: 45326 | B75: 2024 | C75: Febrero | D75: Q1 | E75: Centro | F75: Mayorista | H75: Router WiFi | I75: tecnologia | J75: Redes | K75: Marta Ruiz | L75: 38 | M75: 92850 | N75: 0.08 | O75: 73774.52 | P75: 3528300 | Q75: 3246036 | R75: 442604.24 | S75: Completado
A76: 45362 | B76: 2024 | C76: Marzo | D76: Q1 | E76: Norte | F76: on-line | G76: Cliente 056 | H76: Silla Ergonómica | I76: OFICINA | J76: Mobiliario | K76: juan pérez | L76: 9 | M76: 72322 | O76: 34369.33 | P76: 650898 | Q76: 650898 | R76: 341574.03 | S76: COMPLETADO
A77: 45405 | B77: 2024 | C77: Abril | D77: Q2 | E77: Costa | F77: mayorista | G77: Cliente 015 | H77: Lámpara LED | I77: HOGAR | J77: Iluminación | K77: Luis Gómez | L77: 2 | M77: 57055 | N77: 0.12 | O77: 42289.68 | P77: 114110 | Q77: 100416.8 | R77: 15837.44 | S77: Devuelto
A78: 45425 | B78: 2024 | C78: Mayo | D78: Q2 | E78: Patagonia | F78: RETAIL | G78: Cliente 029 | H78: Mouse Inalámbrico | I78: Tecnología | J78: Accesorios | K78: Sofía García | L78: 11 | M78: 177996 | N78: 0.15 | O78: 136535.92 | P78: 1957956 | Q78: 1664262.6 | R78: 162367.48 | S78: Devuelto
A79: 45452 | B79: 2024 | C79: Junio | D79: Q2 | E79: Sur | F79: ecommerce | G79: Cliente 020 | H79: Teclado Mecánico | I79: tecnologia | J79: Accesorios | K79: Nicolás Ríos | L79: 5 | M79: 176613 | N79: 0.12 | O79: 121579.81 | P79: 883065 | Q79: 777097.2 | R79: 169198.15 | S79: completado
A80: 45488 | B80: 2024 | C80: Julio | D80: Q3 | E80: Norte | F80: mayorista | G80: Cliente 039 | H80: Teclado Mecánico | I80: Tecnología | J80: Accesorios | K80: Nicolás Ríos | L80: 18 | M80: 104259 | N80: 0.2 | O80: 63765.83 | P80: 1876662 | Q80: 1501329.6 | R80: 353544.66 | S80: Completado
A81: 45524 | B81: 2024 | C81: Agosto | D81: Q3 | E81: Interior | F81: mayorista | G81: Cliente 006 | H81: Cafetera | I81: HOGAR | J81: Electrodomésticos | K81: Luis Gómez | L81: 37 | M81: 96286 | N81: 0.1 | O81: 75604.04 | P81: 3562582 | Q81: 3206323.8 | R81: 408974.32 | S81: Anulado
A82: 45541 | B82: 2024 | C82: Septiembre | D82: Q3 | E82: Norte | F82: ecommerce | G82: Cliente 057 | H82: Impresora | I82: oficina | J82: Periféricos | K82: Luis Gómez | L82: 34 | M82: 53614 | N82: 0.2 | O82: 31396.13 | P82: 1822876 | Q82: 1458300.8 | R82: 390832.38 | S82: Devuelto
A83: 45583 | B83: 2024 | C83: Octubre | D83: Q4 | E83: Costa | F83: mayorista | G83: Cliente 033 | H83: Mouse Inalámbrico | I83: Tecnología | J83: Accesorios | K83: Marta Ruiz | L83: 39 | M83: 99388 | N83: 0.1 | O83: 76614.36 | P83: 3876132 | Q83: 3488518.8 | R83: 500558.76 | S83: Devuelto
A84: 45614 | B84: 2024 | C84: Noviembre | D84: Q4 | E84: CABA | F84: market place | G84: Cliente 017 | H84: Silla Ergonómica | I84: Oficina | J84: Mobiliario | K84: Marta Ruiz | L84: 34 | M84: 122993 | N84: 0 | O84: 70955.79 | P84: 4181762 | Q84: 4181762 | R84: 1769265.1 | S84: Pendiente
A85: 45629 | B85: 2024 | C85: Diciembre | D85: Q4 | E85: Centro | F85: ONLINE | G85: Cliente 070 | H85: Teclado Mecánico | I85: tecnologia | J85: Accesorios | K85: Nicolás Ríos | L85: 340 | M85: 174013 | N85: 0.08 | O85: 87700.55 | P85: 59164420 | Q85: 54431266 | R85: 24613079 | S85: Pendiente
A86: 45305 | B86: 2024 | C86: Enero | D86: Q1 | E86: Centro | F86: MARKETPLACE | G86: Cliente 031 | H86: Notebook 14 | I86: tecnologia | J86: Computación | K86: Luis Gómez | L86: 40 | M86: 129683 | N86: 0.15 | O86: 72403.8 | P86: 5187320 | Q86: 4409222 | R86: 1513070 | S86: Anulado
A87: 45347 | B87: 2024 | C87: Febrero | D87: Q1 | E87: Centro | F87: mayorista | G87: Cliente 021 | H87: Auriculares BT | I87: tecnologia | J87: Audio | K87: Nicolás Ríos | L87: 13 | M87: 48280 | N87: 0 | O87: 32560.64 | P87: 627640 | Q87: 627640 | R87: 204351.68 | S87: Devuelto
A88: 45376 | B88: 2024 | C88: Marzo | D88: Q1 | E88: Sur | F88: RETAIL | G88: Cliente 066 | H88: Mouse Inalámbrico | I88: tecnologia | J88: Accesorios | K88: Juan Pérez | L88: 28 | M88: 70205 | O88: 54455.57 | P88: 1965740 | Q88: 1965740 | R88: 440984.04 | S88: Anulado
A89: 45383 | B89: 2024 | C89: Abril | D89: Q2 | E89: Centro | F89: ONLINE | G89: Cliente 043 | H89: Monitor 24 | I89: Tecnología | J89: Imagen | K89: Nicolás Ríos | L89: 10 | M89: 87203 | N89: 0.12 | O89: 60486.2 | P89: 872030 | Q89: 767386.4 | R89: 162524.4 | S89: Pendiente
A90: 45419 | B90: 2024 | C90: Mayo | D90: Q2 | E90: Patagonia | F90: ecommerce | G90: Cliente 068 | H90: Silla Ergonómica | I90: OFICINA | J90: Mobiliario | K90: Luis Gómez | L90: 8 | M90: 74295 | N90: 0 | O90: 39632.95 | P90: 594360 | Q90: 594360 | R90: 277296.4 | S90: COMPLETADO
A91: 45444 | B91: 2024 | C91: Junio | D91: Q2 | E91: Costa | F91: Distribuidor | G91: Cliente 019 | H91: Router WiFi | I91: TECNOLOGÍA | J91: Redes | K91: Sofía García | L91: 280 | M91: 75062 | N91: 0.1 | O91: 51232.06 | P91: 21017360 | Q91: 18915624 | R91: 4570647.2 | S91: Completado
A92: 45474 | B92: 2024 | C92: Julio | D92: Q3 | E92: CABA | F92: Mayorista | G92: Cliente 050 | H92: Router WiFi | I92: Tecnología | J92: Redes | K92: Sofía García | L92: 17 | M92: 105610 | O92: 56437.36 | P92: 1795370 | Q92: 1795370 | R92: 835934.88 | S92: COMPLETADO
A93: 45522 | B93: 2024 | C93: Agosto | D93: Q3 | E93: Centro | F93: Marketplace | G93: Cliente 060 | H93: Escritorio Compacto | I93: OFICINA | J93: Mobiliario | K93: Marta Ruiz | L93: 31 | M93: 47350 | N93: 0.12 | O93: 21920.41 | P93: 1467850 | Q93: 1291708 | R93: 612175.29 | S93: Pendiente
A94: 45562 | B94: 2024 | C94: Septiembre | D94: Q3 | E94: Interior | F94: mayorista | G94: Cliente 005 | H94: Lámpara LED | I94: hogar | J94: Iluminación | K94: Nicolás Ríos | L94: 13 | M94: 24531 | O94: 13384.75 | P94: 318903 | Q94: 318903 | R94: 144901.25 | S94: Devuelto
A95: 45581 | B95: 2024 | C95: Octubre | D95: Q4 | E95: Costa | F95: mayorista | G95: Cliente 067 | H95: Teclado Mecánico | I95: TECNOLOGÍA | J95: Accesorios | K95: Sofía García | L95: 6 | M95: 32690 | N95: 0.1 | O95: 20951.55 | P95: 196140 | Q95: 176526 | R95: 50816.7 | S95: Devuelto
A96: 45602 | B96: 2024 | C96: Noviembre | D96: Q4 | E96: Costa | F96: mayorista | G96: Cliente 058 | H96: Lámpara LED | I96: Hogar | J96: Iluminación | K96: Ana López | L96: 23 | M96: 126017 | N96: 0 | O96: 60017.41 | P96: 2898391 | Q96: 2898391 | R96: 1517990.6 | S96: COMPLETADO
A97: 45654 | B97: 2024 | C97: Diciembre | D97: Q4 | E97: Interior | F97: market place | G97: Cliente 005 | H97: Teclado Mecánico | I97: Tecnología | J97: Accesorios | K97: Juan Pérez | L97: 5 | M97: 108030 | N97: 0 | O97: 71492.44 | P97: 540150 | Q97: 540150 | R97: 182687.8 | S97: COMPLETADO
A98: 45303 | B98: 2024 | C98: Enero | D98: Q1 | E98: CABA | F98: RETAIL | G98: Cliente 032 | H98: Router WiFi | I98: tecnologia | J98: Redes | K98: Ana López | L98: 2 | M98: 142821 | N98: 0.05 | O98: 77354.97 | P98: 285642 | Q98: 271359.9 | R98: 116649.96 | S98: Devuelto
A99: 45326 | B99: 2024 | C99: Febrero | D99: Q1 | E99: Sur | F99: on-line | G99: Cliente 023 | H99: Monitor 24 | I99: TECNOLOGÍA | J99: Imagen | K99: Marta Ruiz | L99: 29 | M99: 95778 | N99: 0.05 | O99: 61537.27 | P99: 2777562 | Q99: 2638683.9 | R99: 854103.07 | S99: Devuelto
A100: 45377 | B100: 2024 | C100: Marzo | D100: Q1 | E100: Centro | F100: Distribuidor | G100: Cliente 016 | H100: Teclado Mecánico | I100: TECNOLOGÍA | J100: Accesorios | K100: Juan Pérez | L100: 9 | M100: 566016 | O100: 347302.91 | P100: 5094144 | Q100: 5094144 | R100: 1968417.8 | S100: completado
A101: 45398 | B101: 2024 | C101: Abril | D101: Q2 | E101: Interior | F101: mayorista | G101: Cliente 010 | H101: Tablet 10 | I101: Tecnología | J101: Movilidad | K101: Juan Pérez | L101: 21 | M101: 129958 | O101: 64318.44 | P101: 2729118 | Q101: 2729118 | R101: 1378430.8 | S101: completado
...

Sheet Aux_Dashboard
A1: Hoja de soporte del Dashboard Final: criterios de filtro, categorías normalizadas y series de los gráficos. No modificar. | R1: Listas para segmentadores
B2: ='Dashboard Final'!$C$12 -> (Todos) | C2: ='Dashboard Final'!$F$12 -> (Todos) | D2: ='Dashboard Final'!$I$12 -> (Todos) | E2: ='Dashboard Final'!$L$12 -> (Todos) | H2: =IF(LEFT(UPPER(Datos_Crudos!I2),3)="TEC","Tecnología",IF(UPPER(Datos_Crudos!I2)="HOGAR","Hogar","Oficina")) -> Oficina | R2: (Todos) | S2: (Todos) | T2: (Todos) | U2: (Todos)
B3: =IF(B2="(Todos)","*",B2) -> * | C3: =IF(C2="(Todos)","*",C2) -> * | D3: =IF(D2="(Todos)","*",D2) -> * | E3: =IF(E2="(Todos)","*",E2) -> * | H3: =IF(LEFT(UPPER(Datos_Crudos!I3),3)="TEC","Tecnología",IF(UPPER(Datos_Crudos!I3)="HOGAR","Hogar","Oficina")) -> Tecnología | R3: Enero | S3: CABA | T3: Tecnología | U3: Completado
H4: =IF(LEFT(UPPER(Datos_Crudos!I4),3)="TEC","Tecnología",IF(UPPER(Datos_Crudos!I4)="HOGAR","Hogar","Oficina")) -> Hogar | R4: Febrero | S4: Centro | T4: Hogar | U4: Pendiente
H5: =IF(LEFT(UPPER(Datos_Crudos!I5),3)="TEC","Tecnología",IF(UPPER(Datos_Crudos!I5)="HOGAR","Hogar","Oficina")) -> Tecnología | R5: Marzo | S5: Costa | T5: Oficina | U5: Anulado
H6: =IF(LEFT(UPPER(Datos_Crudos!I6),3)="TEC","Tecnología",IF(UPPER(Datos_Crudos!I6)="HOGAR","Hogar","Oficina")) -> Tecnología | R6: Abril | S6: Interior | U6: Devuelto
H7: =IF(LEFT(UPPER(Datos_Crudos!I7),3)="TEC","Tecnología",IF(UPPER(Datos_Crudos!I7)="HOGAR","Hogar","Oficina")) -> Tecnología | R7: Mayo | S7: Norte
H8: =IF(LEFT(UPPER(Datos_Crudos!I8),3)="TEC","Tecnología",IF(UPPER(Datos_Crudos!I8)="HOGAR","Hogar","Oficina")) -> Tecnología | R8: Junio | S8: Patagonia
H9: =IF(LEFT(UPPER(Datos_Crudos!I9),3)="TEC","Tecnología",IF(UPPER(Datos_Crudos!I9)="HOGAR","Hogar","Oficina")) -> Tecnología | R9: Julio | S9: Sur
A10: Enero | B10: =SUMIFS(Datos_Crudos!$Q$2:$Q$361,Datos_Crudos!$C$2:$C$361,$A10,Datos_Crudos!$E$2:$E$361,$C$3,$H$2:$H$361,$D$3,Datos_Crudos!$S$2:$S$361,$E$3) -> 74587318 | C10: =SUMIFS(Datos_Crudos!$R$2:$R$361,Datos_Crudos!$C$2:$C$361,$A10,Datos_Crudos!$E$2:$E$361,$C$3,$H$2:$H$361,$D$3,Datos_Crudos!$S$2:$S$361,$E$3) -> 25491254 | D10: =SUMIFS(Datos_Crudos!$L$2:$L$361,Datos_Crudos!$C$2:$C$361,$A10,Datos_Crudos!$E$2:$E$361,$C$3,$H$2:$H$361,$D$3,Datos_Crudos!$S$2:$S$361,$E$3) -> 735 | F10: Tecnología | G10: =SUMIFS(Datos_Crudos!$Q$2:$Q$361,$H$2:$H$361,$F10,Datos_Crudos!$C$2:$C$361,$B$3,Datos_Crudos!$E$2:$E$361,$C$3,Datos_Crudos!$S$2:$S$361,$E$3) -> 5.860561e+08 | H10: =IF(LEFT(UPPER(Datos_Crudos!I10),3)="TEC","Tecnología",IF(UPPER(Datos_Crudos!I10)="HOGAR","Hogar","Oficina")) -> Hogar | J10: Centro | K10: =SUMIFS(Datos_Crudos!$Q$2:$Q$361,Datos_Crudos!$E$2:$E$361,$J10,Datos_Crudos!$C$2:$C$361,$B$3,$H$2:$H$361,$D$3,Datos_Crudos!$S$2:$S$361,$E$3) -> 2.00142e+08 | M10: Cafetera | N10: =SUMIFS(Datos_Crudos!$Q$2:$Q$361,Datos_Crudos!$H$2:$H$361,$M10,Datos_Crudos!$C$2:$C$361,$B$3,Datos_Crudos!$E$2:$E$361,$C$3,$H$2:$H$361,$D$3,Datos_Crudos!$S$2:$S$361,$E$3) -> 1.7418396e+08 | O10: =SUMIFS(Datos_Crudos!$R$2:$R$361,Datos_Crudos!$H$2:$H$361,$M10,Datos_Crudos!$C$2:$C$361,$B$3,Datos_Crudos!$E$2:$E$361,$C$3,$H$2:$H$361,$D$3,Datos_Crudos!$S$2:$S$361,$E$3) -> 64604359 | P10: =IFERROR($O10/$N10,0) -> 0.37089729 | R10: Agosto
A11: Febrero | B11: =SUMIFS(Datos_Crudos!$Q$2:$Q$361,Datos_Crudos!$C$2:$C$361,$A11,Datos_Crudos!$E$2:$E$361,$C$3,$H$2:$H$361,$D$3,Datos_Crudos!$S$2:$S$361,$E$3) -> 59788146 | C11: =SUMIFS(Datos_Crudos!$R$2:$R$361,Datos_Crudos!$C$2:$C$361,$A11,Datos_Crudos!$E$2:$E$361,$C$3,$H$2:$H$361,$D$3,Datos_Crudos!$S$2:$S$361,$E$3) -> 16555685 | D11: =SUMIFS(Datos_Crudos!$L$2:$L$361,Datos_Crudos!$C$2:$C$361,$A11,Datos_Crudos!$E$2:$E$361,$C$3,$H$2:$H$361,$D$3,Datos_Crudos!$S$2:$S$361,$E$3) -> 961 | F11: Hogar | G11: =SUMIFS(Datos_Crudos!$Q$2:$Q$361,$H$2:$H$361,$F11,Datos_Crudos!$C$2:$C$361,$B$3,Datos_Crudos!$E$2:$E$361,$C$3,Datos_Crudos!$S$2:$S$361,$E$3) -> 1.9445864e+08 | H11: =IF(LEFT(UPPER(Datos_Crudos!I11),3)="TEC","Tecnología",IF(UPPER(Datos_Crudos!I11)="HOGAR","Hogar","Oficina")) -> Tecnología | J11: Costa | K11: =SUMIFS(Datos_Crudos!$Q$2:$Q$361,Datos_Crudos!$E$2:$E$361,$J11,Datos_Crudos!$C$2:$C$361,$B$3,$H$2:$H$361,$D$3,Datos_Crudos!$S$2:$S$361,$E$3) -> 1.6825941e+08 | M11: Monitor 24 | N11: =SUMIFS(Datos_Crudos!$Q$2:$Q$361,Datos_Crudos!$H$2:$H$361,$M11,Datos_Crudos!$C$2:$C$361,$B$3,Datos_Crudos!$E$2:$E$361,$C$3,$H$2:$H$361,$D$3,Datos_Crudos!$S$2:$S$361,$E$3) -> 1.3641004e+08 | O11: =SUMIFS(Datos_Crudos!$R$2:$R$361,Datos_Crudos!$H$2:$H$361,$M11,Datos_Crudos!$C$2:$C$361,$B$3,Datos_Crudos!$E$2:$E$361,$C$3,$H$2:$H$361,$D$3,Datos_Crudos!$S$2:$S$361,$E$3) -> 48935363 | P11: =IFERROR($O11/$N11,0) -> 0.35873725 | R11: Septiembre
A12: Marzo | B12: =SUMIFS(Datos_Crudos!$Q$2:$Q$361,Datos_Crudos!$C$2:$C$361,$A12,Datos_Crudos!$E$2:$E$361,$C$3,$H$2:$H$361,$D$3,Datos_Crudos!$S$2:$S$361,$E$3) -> 95487410 | C12: =SUMIFS(Datos_Crudos!$R$2:$R$361,Datos_Crudos!$C$2:$C$361,$A12,Datos_Crudos!$E$2:$E$361,$C$3,$H$2:$H$361,$D$3,Datos_Crudos!$S$2:$S$361,$E$3) -> 36813684 | D12: =SUMIFS(Datos_Crudos!$L$2:$L$361,Datos_Crudos!$C$2:$C$361,$A12,Datos_Crudos!$E$2:$E$361,$C$3,$H$2:$H$361,$D$3,Datos_Crudos!$S$2:$S$361,$E$3) -> 1122 | F12: Oficina | G12: =SUMIFS(Datos_Crudos!$Q$2:$Q$361,$H$2:$H$361,$F12,Datos_Crudos!$C$2:$C$361,$B$3,Datos_Crudos!$E$2:$E$361,$C$3,Datos_Crudos!$S$2:$S$361,$E$3) -> 2.0708205e+08 | H12: =IF(LEFT(UPPER(Datos_Crudos!I12),3)="TEC","Tecnología",IF(UPPER(Datos_Crudos!I12)="HOGAR","Hogar","Oficina")) -> Tecnología | J12: Norte | K12: =SUMIFS(Datos_Crudos!$Q$2:$Q$361,Datos_Crudos!$E$2:$E$361,$J12,Datos_Crudos!$C$2:$C$361,$B$3,$H$2:$H$361,$D$3,Datos_Crudos!$S$2:$S$361,$E$3) -> 1.5498669e+08 | M12: Teclado Mecánico | N12: =SUMIFS(Datos_Crudos!$Q$2:$Q$361,Datos_Crudos!$H$2:$H$361,$M12,Datos_Crudos!$C$2:$C$361,$B$3,Datos_Crudos!$E$2:$E$361,$C$3,$H$2:$H$361,$D$3,Datos_Crudos!$S$2:$S$361,$E$3) -> 1.1650021e+08 | O12: =SUMIFS(Datos_Crudos!$R$2:$R$361,Datos_Crudos!$H$2:$H$361,$M12,Datos_Crudos!$C$2:$C$361,$B$3,Datos_Crudos!$E$2:$E$361,$C$3,$H$2:$H$361,$D$3,Datos_Crudos!$S$2:$S$361,$E$3) -> 42776574 | P12: =IFERROR($O12/$N12,0) -> 0.36718025 | R12: Octubre
A13: Abril | B13: =SUMIFS(Datos_Crudos!$Q$2:$Q$361,Datos_Crudos!$C$2:$C$361,$A13,Datos_Crudos!$E$2:$E$361,$C$3,$H$2:$H$361,$D$3,Datos_Crudos!$S$2:$S$361,$E$3) -> 50180273 | C13: =SUMIFS(Datos_Crudos!$R$2:$R$361,Datos_Crudos!$C$2:$C$361,$A13,Datos_Crudos!$E$2:$E$361,$C$3,$H$2:$H$361,$D$3,Datos_Crudos!$S$2:$S$361,$E$3) -> 15001026 | D13: =SUMIFS(Datos_Crudos!$L$2:$L$361,Datos_Crudos!$C$2:$C$361,$A13,Datos_Crudos!$E$2:$E$361,$C$3,$H$2:$H$361,$D$3,Datos_Crudos!$S$2:$S$361,$E$3) -> 564 | H13: =IF(LEFT(UPPER(Datos_Crudos!I13),3)="TEC","Tecnología",IF(UPPER(Datos_Crudos!I13)="HOGAR","Hogar","Oficina")) -> Tecnología | J13: CABA | K13: =SUMIFS(Datos_Crudos!$Q$2:$Q$361,Datos_Crudos!$E$2:$E$361,$J13,Datos_Crudos!$C$2:$C$361,$B$3,$H$2:$H$361,$D$3,Datos_Crudos!$S$2:$S$361,$E$3) -> 1.4163438e+08 | M13: Tablet 10 | N13: =SUMIFS(Datos_Crudos!$Q$2:$Q$361,Datos_Crudos!$H$2:$H$361,$M13,Datos_Crudos!$C$2:$C$361,$B$3,Datos_Crudos!$E$2:$E$361,$C$3,$H$2:$H$361,$D$3,Datos_Crudos!$S$2:$S$361,$E$3) -> 84910390 | O13: =SUMIFS(Datos_Crudos!$R$2:$R$361,Datos_Crudos!$H$2:$H$361,$M13,Datos_Crudos!$C$2:$C$361,$B$3,Datos_Crudos!$E$2:$E$361,$C$3,$H$2:$H$361,$D$3,Datos_Crudos!$S$2:$S$361,$E$3) -> 35104848 | P13: =IFERROR($O13/$N13,0) -> 0.41343407 | R13: Noviembre
A14: Mayo | B14: =SUMIFS(Datos_Crudos!$Q$2:$Q$361,Datos_Crudos!$C$2:$C$361,$A14,Datos_Crudos!$E$2:$E$361,$C$3,$H$2:$H$361,$D$3,Datos_Crudos!$S$2:$S$361,$E$3) -> 63280396 | C14: =SUMIFS(Datos_Crudos!$R$2:$R$361,Datos_Crudos!$C$2:$C$361,$A14,Datos_Crudos!$E$2:$E$361,$C$3,$H$2:$H$361,$D$3,Datos_Crudos!$S$2:$S$361,$E$3) -> 23107822 | D14: =SUMIFS(Datos_Crudos!$L$2:$L$361,Datos_Crudos!$C$2:$C$361,$A14,Datos_Crudos!$E$2:$E$361,$C$3,$H$2:$H$361,$D$3,Datos_Crudos!$S$2:$S$361,$E$3) -> 804 | H14: =IF(LEFT(UPPER(Datos_Crudos!I14),3)="TEC","Tecnología",IF(UPPER(Datos_Crudos!I14)="HOGAR","Hogar","Oficina")) -> Hogar | J14: Sur | K14: =SUMIFS(Datos_Crudos!$Q$2:$Q$361,Datos_Crudos!$E$2:$E$361,$J14,Datos_Crudos!$C$2:$C$361,$B$3,$H$2:$H$361,$D$3,Datos_Crudos!$S$2:$S$361,$E$3) -> 1.3066627e+08 | M14: Router WiFi | N14: =SUMIFS(Datos_Crudos!$Q$2:$Q$361,Datos_Crudos!$H$2:$H$361,$M14,Datos_Crudos!$C$2:$C$361,$B$3,Datos_Crudos!$E$2:$E$361,$C$3,$H$2:$H$361,$D$3,Datos_Crudos!$S$2:$S$361,$E$3) -> 79120954 | O14: =SUMIFS(Datos_Crudos!$R$2:$R$361,Datos_Crudos!$H$2:$H$361,$M14,Datos_Crudos!$C$2:$C$361,$B$3,Datos_Crudos!$E$2:$E$361,$C$3,$H$2:$H$361,$D$3,Datos_Crudos!$S$2:$S$361,$E$3) -> 23477805 | P14: =IFERROR($O14/$N14,0) -> 0.29673309 | R14: Diciembre
A15: Junio | B15: =SUMIFS(Datos_Crudos!$Q$2:$Q$361,Datos_Crudos!$C$2:$C$361,$A15,Datos_Crudos!$E$2:$E$361,$C$3,$H$2:$H$361,$D$3,Datos_Crudos!$S$2:$S$361,$E$3) -> 93736031 | C15: =SUMIFS(Datos_Crudos!$R$2:$R$361,Datos_Crudos!$C$2:$C$361,$A15,Datos_Crudos!$E$2:$E$361,$C$3,$H$2:$H$361,$D$3,Datos_Crudos!$S$2:$S$361,$E$3) -> 34250147 | D15: =SUMIFS(Datos_Crudos!$L$2:$L$361,Datos_Crudos!$C$2:$C$361,$A15,Datos_Crudos!$E$2:$E$361,$C$3,$H$2:$H$361,$D$3,Datos_Crudos!$S$2:$S$361,$E$3) -> 1112 | H15: =IF(LEFT(UPPER(Datos_Crudos!I15),3)="TEC","Tecnología",IF(UPPER(Datos_Crudos!I15)="HOGAR","Hogar","Oficina")) -> Tecnología | J15: Patagonia | K15: =SUMIFS(Datos_Crudos!$Q$2:$Q$361,Datos_Crudos!$E$2:$E$361,$J15,Datos_Crudos!$C$2:$C$361,$B$3,$H$2:$H$361,$D$3,Datos_Crudos!$S$2:$S$361,$E$3) -> 1.2020478e+08 | M15: Impresora | N15: =SUMIFS(Datos_Crudos!$Q$2:$Q$361,Datos_Crudos!$H$2:$H$361,$M15,Datos_Crudos!$C$2:$C$361,$B$3,Datos_Crudos!$E$2:$E$361,$C$3,$H$2:$H$361,$D$3,Datos_Crudos!$S$2:$S$361,$E$3) -> 75854180 | O15: =SUMIFS(Datos_Crudos!$R$2:$R$361,Datos_Crudos!$H$2:$H$361,$M15,Datos_Crudos!$C$2:$C$361,$B$3,Datos_Crudos!$E$2:$E$361,$C$3,$H$2:$H$361,$D$3,Datos_Crudos!$S$2:$S$361,$E$3) -> 22122417 | P15: =IFERROR($O15/$N15,0) -> 0.29164401
A16: Julio | B16: =SUMIFS(Datos_Crudos!$Q$2:$Q$361,Datos_Crudos!$C$2:$C$361,$A16,Datos_Crudos!$E$2:$E$361,$C$3,$H$2:$H$361,$D$3,Datos_Crudos!$S$2:$S$361,$E$3) -> 1.2501894e+08 | C16: =SUMIFS(Datos_Crudos!$R$2:$R$361,Datos_Crudos!$C$2:$C$361,$A16,Datos_Crudos!$E$2:$E$361,$C$3,$H$2:$H$361,$D$3,Datos_Crudos!$S$2:$S$361,$E$3) -> 45527917 | D16: =SUMIFS(Datos_Crudos!$L$2:$L$361,Datos_Crudos!$C$2:$C$361,$A16,Datos_Crudos!$E$2:$E$361,$C$3,$H$2:$H$361,$D$3,Datos_Crudos!$S$2:$S$361,$E$3) -> 1376 | H16: =IF(LEFT(UPPER(Datos_Crudos!I16),3)="TEC","Tecnología",IF(UPPER(Datos_Crudos!I16)="HOGAR","Hogar","Oficina")) -> Oficina | J16: Interior | K16: =SUMIFS(Datos_Crudos!$Q$2:$Q$361,Datos_Crudos!$E$2:$E$361,$J16,Datos_Crudos!$C$2:$C$361,$B$3,$H$2:$H$361,$D$3,Datos_Crudos!$S$2:$S$361,$E$3) -> 71703251 | M16: Escritorio Compacto | N16: =SUMIFS(Datos_Crudos!$Q$2:$Q$361,Datos_Crudos!$H$2:$H$361,$M16,Datos_Crudos!$C$2:$C$361,$B$3,Datos_Crudos!$E$2:$E$361,$C$3,$H$2:$H$361,$D$3,Datos_Crudos!$S$2:$S$361,$E$3) -> 74942474 | O16: =SUMIFS(Datos_Crudos!$R$2:$R$361,Datos_Crudos!$H$2:$H$361,$M16,Datos_Crudos!$C$2:$C$361,$B$3,Datos_Crudos!$E$2:$E$361,$C$3,$H$2:$H$361,$D$3,Datos_Crudos!$S$2:$S$361,$E$3) -> 26309456 | P16: =IFERROR($O16/$N16,0) -> 0.35106201
A17: Agosto | B17: =SUMIFS(Datos_Crudos!$Q$2:$Q$361,Datos_Crudos!$C$2:$C$361,$A17,Datos_Crudos!$E$2:$E$361,$C$3,$H$2:$H$361,$D$3,Datos_Crudos!$S$2:$S$361,$E$3) -> 62673741 | C17: =SUMIFS(Datos_Crudos!$R$2:$R$361,Datos_Crudos!$C$2:$C$361,$A17,Datos_Crudos!$E$2:$E$361,$C$3,$H$2:$H$361,$D$3,Datos_Crudos!$S$2:$S$361,$E$3) -> 19261078 | D17: =SUMIFS(Datos_Crudos!$L$2:$L$361,Datos_Crudos!$C$2:$C$361,$A17,Datos_Crudos!$E$2:$E$361,$C$3,$H$2:$H$361,$D$3,Datos_Crudos!$S$2:$S$361,$E$3) -> 668 | H17: =IF(LEFT(UPPER(Datos_Crudos!I17),3)="TEC","Tecnología",IF(UPPER(Datos_Crudos!I17)="HOGAR","Hogar","Oficina")) -> Tecnología | M17: Mouse Inalámbrico | N17: =SUMIFS(Datos_Crudos!$Q$2:$Q$361,Datos_Crudos!$H$2:$H$361,$M17,Datos_Crudos!$C$2:$C$361,$B$3,Datos_Crudos!$E$2:$E$361,$C$3,$H$2:$H$361,$D$3,Datos_Crudos!$S$2:$S$361,$E$3) -> 70563336 | O17: =SUMIFS(Datos_Crudos!$R$2:$R$361,Datos_Crudos!$H$2:$H$361,$M17,Datos_Crudos!$C$2:$C$361,$B$3,Datos_Crudos!$E$2:$E$361,$C$3,$H$2:$H$361,$D$3,Datos_Crudos!$S$2:$S$361,$E$3) -> 22301135 | P17: =IFERROR($O17/$N17,0) -> 0.31604422
A18: Septiembre | B18: =SUMIFS(Datos_Crudos!$Q$2:$Q$361,Datos_Crudos!$C$2:$C$361,$A18,Datos_Crudos!$E$2:$E$361,$C$3,$H$2:$H$361,$D$3,Datos_Crudos!$S$2:$S$361,$E$3) -> 59677427 | C18: =SUMIFS(Datos_Crudos!$R$2:$R$361,Datos_Crudos!$C$2:$C$361,$A18,Datos_Crudos!$E$2:$E$361,$C$3,$H$2:$H$361,$D$3,Datos_Crudos!$S$2:$S$361,$E$3) -> 16746029 | D18: =SUMIFS(Datos_Crudos!$L$2:$L$361,Datos_Crudos!$C$2:$C$361,$A18,Datos_Crudos!$E$2:$E$361,$C$3,$H$2:$H$361,$D$3,Datos_Crudos!$S$2:$S$361,$E$3) -> 675 | H18: =IF(LEFT(UPPER(Datos_Crudos!I18),3)="TEC","Tecnología",IF(UPPER(Datos_Crudos!I18)="HOGAR","Hogar","Oficina")) -> Tecnología | M18: Silla Ergonómica | N18: =SUMIFS(Datos_Crudos!$Q$2:$Q$361,Datos_Crudos!$H$2:$H$361,$M18,Datos_Crudos!$C$2:$C$361,$B$3,Datos_Crudos!$E$2:$E$361,$C$3,$H$2:$H$361,$D$3,Datos_Crudos!$S$2:$S$361,$E$3) -> 56285393 | O18: =SUMIFS(Datos_Crudos!$R$2:$R$361,Datos_Crudos!$H$2:$H$361,$M18,Datos_Crudos!$C$2:$C$361,$B$3,Datos_Crudos!$E$2:$E$361,$C$3,$H$2:$H$361,$D$3,Datos_Crudos!$S$2:$S$361,$E$3) -> 17910219 | P18: =IFERROR($O18/$N18,0) -> 0.31820369
A19: Octubre | B19: =SUMIFS(Datos_Crudos!$Q$2:$Q$361,Datos_Crudos!$C$2:$C$361,$A19,Datos_Crudos!$E$2:$E$361,$C$3,$H$2:$H$361,$D$3,Datos_Crudos!$S$2:$S$361,$E$3) -> 86928102 | C19: =SUMIFS(Datos_Crudos!$R$2:$R$361,Datos_Crudos!$C$2:$C$361,$A19,Datos_Crudos!$E$2:$E$361,$C$3,$H$2:$H$361,$D$3,Datos_Crudos!$S$2:$S$361,$E$3) -> 26810874 | D19: =SUMIFS(Datos_Crudos!$L$2:$L$361,Datos_Crudos!$C$2:$C$361,$A19,Datos_Crudos!$E$2:$E$361,$C$3,$H$2:$H$361,$D$3,Datos_Crudos!$S$2:$S$361,$E$3) -> 763 | H19: =IF(LEFT(UPPER(Datos_Crudos!I19),3)="TEC","Tecnología",IF(UPPER(Datos_Crudos!I19)="HOGAR","Hogar","Oficina")) -> Oficina | M19: Auriculares BT | N19: =SUMIFS(Datos_Crudos!$Q$2:$Q$361,Datos_Crudos!$H$2:$H$361,$M19,Datos_Crudos!$C$2:$C$361,$B$3,Datos_Crudos!$E$2:$E$361,$C$3,$H$2:$H$361,$D$3,Datos_Crudos!$S$2:$S$361,$E$3) -> 53910056 | O19: =SUMIFS(Datos_Crudos!$R$2:$R$361,Datos_Crudos!$H$2:$H$361,$M19,Datos_Crudos!$C$2:$C$361,$B$3,Datos_Crudos!$E$2:$E$361,$C$3,$H$2:$H$361,$D$3,Datos_Crudos!$S$2:$S$361,$E$3) -> 20843076 | P19: =IFERROR($O19/$N19,0) -> 0.38662686
A20: Noviembre | B20: =SUMIFS(Datos_Crudos!$Q$2:$Q$361,Datos_Crudos!$C$2:$C$361,$A20,Datos_Crudos!$E$2:$E$361,$C$3,$H$2:$H$361,$D$3,Datos_Crudos!$S$2:$S$361,$E$3) -> 1.0078942e+08 | C20: =SUMIFS(Datos_Crudos!$R$2:$R$361,Datos_Crudos!$C$2:$C$361,$A20,Datos_Crudos!$E$2:$E$361,$C$3,$H$2:$H$361,$D$3,Datos_Crudos!$S$2:$S$361,$E$3) -> 36077855 | D20: =SUMIFS(Datos_Crudos!$L$2:$L$361,Datos_Crudos!$C$2:$C$361,$A20,Datos_Crudos!$E$2:$E$361,$C$3,$H$2:$H$361,$D$3,Datos_Crudos!$S$2:$S$361,$E$3) -> 1297 | H20: =IF(LEFT(UPPER(Datos_Crudos!I20),3)="TEC","Tecnología",IF(UPPER(Datos_Crudos!I20)="HOGAR","Hogar","Oficina")) -> Tecnología | M20: Notebook 14 | N20: =SUMIFS(Datos_Crudos!$Q$2:$Q$361,Datos_Crudos!$H$2:$H$361,$M20,Datos_Crudos!$C$2:$C$361,$B$3,Datos_Crudos!$E$2:$E$361,$C$3,$H$2:$H$361,$D$3,Datos_Crudos!$S$2:$S$361,$E$3) -> 44641119 | O20: =SUMIFS(Datos_Crudos!$R$2:$R$361,Datos_Crudos!$H$2:$H$361,$M20,Datos_Crudos!$C$2:$C$361,$B$3,Datos_Crudos!$E$2:$E$361,$C$3,$H$2:$H$361,$D$3,Datos_Crudos!$S$2:$S$361,$E$3) -> 13525265 | P20: =IFERROR($O20/$N20,0) -> 0.30297773
A21: Diciembre | B21: =SUMIFS(Datos_Crudos!$Q$2:$Q$361,Datos_Crudos!$C$2:$C$361,$A21,Datos_Crudos!$E$2:$E$361,$C$3,$H$2:$H$361,$D$3,Datos_Crudos!$S$2:$S$361,$E$3) -> 1.1544958e+08 | C21: =SUMIFS(Datos_Crudos!$R$2:$R$361,Datos_Crudos!$C$2:$C$361,$A21,Datos_Crudos!$E$2:$E$361,$C$3,$H$2:$H$361,$D$3,Datos_Crudos!$S$2:$S$361,$E$3) -> 48322654 | D21: =SUMIFS(Datos_Crudos!$L$2:$L$361,Datos_Crudos!$C$2:$C$361,$A21,Datos_Crudos!$E$2:$E$361,$C$3,$H$2:$H$361,$D$3,Datos_Crudos!$S$2:$S$361,$E$3) -> 1119 | H21: =IF(LEFT(UPPER(Datos_Crudos!I21),3)="TEC","Tecnología",IF(UPPER(Datos_Crudos!I21)="HOGAR","Hogar","Oficina")) -> Tecnología | M21: Lámpara LED | N21: =SUMIFS(Datos_Crudos!$Q$2:$Q$361,Datos_Crudos!$H$2:$H$361,$M21,Datos_Crudos!$C$2:$C$361,$B$3,Datos_Crudos!$E$2:$E$361,$C$3,$H$2:$H$361,$D$3,Datos_Crudos!$S$2:$S$361,$E$3) -> 20274678 | O21: =SUMIFS(Datos_Crudos!$R$2:$R$361,Datos_Crudos!$H$2:$H$361,$M21,Datos_Crudos!$C$2:$C$361,$B$3,Datos_Crudos!$E$2:$E$361,$C$3,$H$2:$H$361,$D$3,Datos_Crudos!$S$2:$S$361,$E$3) -> 6055507.6 | P21: =IFERROR($O21/$N21,0) -> 0.29867342
B22: =IFERROR(MATCH($B$2,$A$10:$A$21,0),0) -> 0 | H22: =IF(LEFT(UPPER(Datos_Crudos!I22),3)="TEC","Tecnología",IF(UPPER(Datos_Crudos!I22)="HOGAR","Hogar","Oficina")) -> Tecnología
H23: =IF(LEFT(UPPER(Datos_Crudos!I23),3)="TEC","Tecnología",IF(UPPER(Datos_Crudos!I23)="HOGAR","Hogar","Oficina")) -> Tecnología
B24: =IF($B$22=0,SUM($B$10:$B$21),INDEX($B$10:$B$21,$B$22)) -> 9.8759678e+08 | C24: =IF($B$22=0,SUM($C$10:$C$21),INDEX($C$10:$C$21,$B$22)) -> 3.4396602e+08 | D24: =IF($B$22=0,SUM($D$10:$D$21),INDEX($D$10:$D$21,$B$22)) -> 11196 | E24: =IFERROR($C$24/$B$24,0) -> 0.34828589 | F24: =IFERROR($B$24/$D$24,0) -> 88209.788 | H24: =IF(LEFT(UPPER(Datos_Crudos!I24),3)="TEC","Tecnología",IF(UPPER(Datos_Crudos!I24)="HOGAR","Hogar","Oficina")) -> Tecnología
B25: =IF($B$22=0,SUM($B$16:$B$21),B24) -> 5.5053721e+08 | C25: =IF($B$22=0,SUM($C$16:$C$21),C24) -> 1.9274641e+08 | D25: =IF($B$22=0,SUM($D$16:$D$21),D24) -> 5898 | E25: =IFERROR($C$25/$B$25,0) -> 0.35010605 | F25: =IFERROR($B$25/$D$25,0) -> 93343.033 | H25: =IF(LEFT(UPPER(Datos_Crudos!I25),3)="TEC","Tecnología",IF(UPPER(Datos_Crudos!I25)="HOGAR","Hogar","Oficina")) -> Oficina
B26: =IF($B$22=0,SUM($B$10:$B$15),IF($B$22=1,AVERAGE($B$10:$B$21),INDEX($B$10:$B$21,$B$22-1))) -> 4.3705957e+08 | C26: =IF($B$22=0,SUM($C$10:$C$15),IF($B$22=1,AVERAGE($C$10:$C$21),INDEX($C$10:$C$21,$B$22-1))) -> 1.5121962e+08 | D26: =IF($B$22=0,SUM($D$10:$D$15),IF($B$22=1,AVERAGE($D$10:$D$21),INDEX($D$10:$D$21,$B$22-1))) -> 5298 | E26: =IFERROR($C$26/$B$26,0) -> 0.34599315 | F26: =IFERROR($B$26/$D$26,0) -> 82495.201 | H26: =IF(LEFT(UPPER(Datos_Crudos!I26),3)="TEC","Tecnología",IF(UPPER(Datos_Crudos!I26)="HOGAR","Hogar","Oficina")) -> Tecnología
B27: =IFERROR($B$25/$B$26-1,0) -> 0.25963883 | D27: =IFERROR($D$25/$D$26-1,0) -> 0.11325028 | E27: =$E$25-$E$26 -> 0.0041128992 | F27: =IFERROR($F$25/$F$26-1,0) -> 0.13149653 | H27: =IF(LEFT(UPPER(Datos_Crudos!I27),3)="TEC","Tecnología",IF(UPPER(Datos_Crudos!I27)="HOGAR","Hogar","Oficina")) -> Hogar
H28: =IF(LEFT(UPPER(Datos_Crudos!I28),3)="TEC","Tecnología",IF(UPPER(Datos_Crudos!I28)="HOGAR","Hogar","Oficina")) -> Tecnología
B29: =IF($B$22=0,"2º semestre vs 1º semestre",IF($B$22=1,"enero vs promedio mensual","vs mes anterior")) -> 2º semestre vs 1º semestre | H29: =IF(LEFT(UPPER(Datos_Crudos!I29),3)="TEC","Tecnología",IF(UPPER(Datos_Crudos!I29)="HOGAR","Hogar","Oficina")) -> Hogar
H30: =IF(LEFT(UPPER(Datos_Crudos!I30),3)="TEC","Tecnología",IF(UPPER(Datos_Crudos!I30)="HOGAR","Hogar","Oficina")) -> Tecnología
B31: ="Año 2024 · Mes: "&$B$2&" · Región: "&$C$2&" · Categoría: "&$D$2&" · Estado: "&$E$2 -> Año 2024 · Mes: (Todos) · Región: (Todos) · Categoría: (Todos) · Estado: (Todos) | H31: =IF(LEFT(UPPER(Datos_Crudos!I31),3)="TEC","Tecnología",IF(UPPER(Datos_Crudos!I31)="HOGAR","Hogar","Oficina")) -> Tecnología
B32: =IF(SUM($B$10:$B$21)=0,"Sin datos para la selección actual","Las ventas alcanzan su máximo en "&INDEX($A$10:$A$21,MATCH(MAX($B$10:$B$21),$B$10:$B$21,0))) -> Las ventas alcanzan su máximo en Julio | H32: =IF(LEFT(UPPER(Datos_Crudos!I32),3)="TEC","Tecnología",IF(UPPER(Datos_Crudos!I32)="HOGAR","Hogar","Oficina")) -> Tecnología
B33: =IF(SUM($G$10:$G$12)=0,"Sin datos para la selección actual","La categoría "&INDEX($F$10:$F$12,MATCH(MAX($G$10:$G$12),$G$10:$G$12,0))&" concentra la mayor venta del período") -> La categoría Tecnología concentra la mayor venta del período | H33: =IF(LEFT(UPPER(Datos_Crudos!I33),3)="TEC","Tecnología",IF(UPPER(Datos_Crudos!I33)="HOGAR","Hogar","Oficina")) -> Tecnología
B34: =IF(SUM($K$10:$K$16)=0,"Sin datos para la selección actual","La región "&INDEX($J$10:$J$16,MATCH(MAX($K$10:$K$16),$K$10:$K$16,0))&" lidera las ventas del período") -> La región Centro lidera las ventas del período | H34: =IF(LEFT(UPPER(Datos_Crudos!I34),3)="TEC","Tecnología",IF(UPPER(Datos_Crudos!I34)="HOGAR","Hogar","Oficina")) -> Hogar
B35: Ventas vs. % de margen por producto (casos atípicos) | H35: =IF(LEFT(UPPER(Datos_Crudos!I35),3)="TEC","Tecnología",IF(UPPER(Datos_Crudos!I35)="HOGAR","Hogar","Oficina")) -> Tecnología
B36: =IF(SUM($N$10:$N$21)=0,"Sin datos para la selección actual","Mayor % de margen: "&INDEX($M$10:$M$21,MATCH(MAX($P$10:$P$21),$P$10:$P$21,0))&" · Menor: "&INDEX($M$10:$M$21,MATCH(MIN($P$10:$P$21),$P$10:$P$21,0))) -> Mayor % de margen: Tablet 10 · Menor: Impresora | H36: =IF(LEFT(UPPER(Datos_Crudos!I36),3)="TEC","Tecnología",IF(UPPER(Datos_Crudos!I36)="HOGAR","Hogar","Oficina")) -> Tecnología
B37: =IF($B$22=0,"Total 2024",$B$2&" 2024") -> Total 2024 | H37: =IF(LEFT(UPPER(Datos_Crudos!I37),3)="TEC","Tecnología",IF(UPPER(Datos_Crudos!I37)="HOGAR","Hogar","Oficina")) -> Tecnología
H38: =IF(LEFT(UPPER(Datos_Crudos!I38),3)="TEC","Tecnología",IF(UPPER(Datos_Crudos!I38)="HOGAR","Hogar","Oficina")) -> Tecnología
H39: =IF(LEFT(UPPER(Datos_Crudos!I39),3)="TEC","Tecnología",IF(UPPER(Datos_Crudos!I39)="HOGAR","Hogar","Oficina")) -> Tecnología
H40: =IF(LEFT(UPPER(Datos_Crudos!I40),3)="TEC","Tecnología",IF(UPPER(Datos_Crudos!I40)="HOGAR","Hogar","Oficina")) -> Tecnología
H41: =IF(LEFT(UPPER(Datos_Crudos!I41),3)="TEC","Tecnología",IF(UPPER(Datos_Crudos!I41)="HOGAR","Hogar","Oficina")) -> Tecnología
H42: =IF(LEFT(UPPER(Datos_Crudos!I42),3)="TEC","Tecnología",IF(UPPER(Datos_Crudos!I42)="HOGAR","Hogar","Oficina")) -> Oficina
H43: =IF(LEFT(UPPER(Datos_Crudos!I43),3)="TEC","Tecnología",IF(UPPER(Datos_Crudos!I43)="HOGAR","Hogar","Oficina")) -> Oficina
H44: =IF(LEFT(UPPER(Datos_Crudos!I44),3)="TEC","Tecnología",IF(UPPER(Datos_Crudos!I44)="HOGAR","Hogar","Oficina")) -> Tecnología
H45: =IF(LEFT(UPPER(Datos_Crudos!I45),3)="TEC","Tecnología",IF(UPPER(Datos_Crudos!I45)="HOGAR","Hogar","Oficina")) -> Hogar
H46: =IF(LEFT(UPPER(Datos_Crudos!I46),3)="TEC","Tecnología",IF(UPPER(Datos_Crudos!I46)="HOGAR","Hogar","Oficina")) -> Oficina
H47: =IF(LEFT(UPPER(Datos_Crudos!I47),3)="TEC","Tecnología",IF(UPPER(Datos_Crudos!I47)="HOGAR","Hogar","Oficina")) -> Tecnología
H48: =IF(LEFT(UPPER(Datos_Crudos!I48),3)="TEC","Tecnología",IF(UPPER(Datos_Crudos!I48)="HOGAR","Hogar","Oficina")) -> Tecnología
H49: =IF(LEFT(UPPER(Datos_Crudos!I49),3)="TEC","Tecnología",IF(UPPER(Datos_Crudos!I49)="HOGAR","Hogar","Oficina")) -> Oficina
... H361: =IF(LEFT(UPPER(Datos_Crudos!I361),3)="TEC","Tecnología",IF(UPPER(Datos_Crudos!I361)="HOGAR","Hogar","Oficina")) -> Tecnología
